{
  "nodes": {
    "SitePage /dev-404-page/": {
      "layout": "index",
      "jsonName": "dev-404-page.json",
      "internalComponentName": "ComponentDev404Page",
      "path": "/dev-404-page/",
      "component": "/home/viktor/Work/homepage/.cache/dev-404-page.js",
      "componentChunkName": "component---cache-dev-404-page-js",
      "context": {},
      "pluginCreator___NODE": "Plugin dev-404-page",
      "pluginCreatorId": "Plugin dev-404-page",
      "componentPath": "/home/viktor/Work/homepage/.cache/dev-404-page.js",
      "id": "SitePage /dev-404-page/",
      "parent": "SOURCE",
      "children": [],
      "internal": {
        "type": "SitePage",
        "contentDigest": "303dfecf5c9aa39dba576979001e2eac",
        "description": "Plugin dev-404-page",
        "owner": "internal-data-bridge"
      }
    },
    "Plugin dev-404-page": {
      "resolve": "/home/viktor/Work/homepage/node_modules/gatsby/dist/internal-plugins/dev-404-page",
      "id": "Plugin dev-404-page",
      "name": "dev-404-page",
      "version": "1.0.0",
      "pluginOptions": {
        "plugins": []
      },
      "nodeAPIs": [
        "createPagesStatefully"
      ],
      "browserAPIs": [],
      "ssrAPIs": [],
      "pluginFilepath": "/home/viktor/Work/homepage/node_modules/gatsby/dist/internal-plugins/dev-404-page",
      "packageJson": {
        "name": "dev-404-page",
        "description": "Internal plugin to add a 404 page in development with helpful information",
        "version": "1.0.0",
        "main": "index.js",
        "author": "Kyle Mathews <mathews.kyle@gmail.com>",
        "license": "MIT",
        "dependencies": [],
        "devDependencies": [],
        "peerDependencies": [],
        "optionalDependecies": [],
        "bundledDependecies": []
      },
      "parent": "SOURCE",
      "children": [],
      "internal": {
        "contentDigest": "76b3416ad7817b7e5d8757a005f47dee",
        "type": "SitePlugin",
        "owner": "internal-data-bridge"
      }
    },
    "Plugin component-page-creator": {
      "resolve": "/home/viktor/Work/homepage/node_modules/gatsby/dist/internal-plugins/component-page-creator",
      "id": "Plugin component-page-creator",
      "name": "component-page-creator",
      "version": "1.0.0",
      "pluginOptions": {
        "plugins": []
      },
      "nodeAPIs": [
        "createPagesStatefully"
      ],
      "browserAPIs": [],
      "ssrAPIs": [],
      "pluginFilepath": "/home/viktor/Work/homepage/node_modules/gatsby/dist/internal-plugins/component-page-creator",
      "packageJson": {
        "name": "component-page-creator",
        "description": "An internal Gatsby plugin that creates pages from component files in src/pages",
        "version": "1.0.0",
        "main": "index.js",
        "keywords": [
          "gatsby",
          "gatsby-plugin"
        ],
        "author": "Kyle Mathews <mathews.kyle@gmail.com>",
        "license": "MIT",
        "dependencies": [],
        "devDependencies": [],
        "peerDependencies": [],
        "optionalDependecies": [],
        "bundledDependecies": []
      },
      "parent": "SOURCE",
      "children": [],
      "internal": {
        "contentDigest": "ed9e73f85c724a77319ce417a2b81d35",
        "type": "SitePlugin",
        "owner": "internal-data-bridge"
      }
    },
    "Plugin component-layout-creator": {
      "resolve": "/home/viktor/Work/homepage/node_modules/gatsby/dist/internal-plugins/component-layout-creator",
      "id": "Plugin component-layout-creator",
      "name": "component-layout-creator",
      "version": "1.0.0",
      "pluginOptions": {
        "plugins": []
      },
      "nodeAPIs": [
        "createLayouts"
      ],
      "browserAPIs": [],
      "ssrAPIs": [],
      "pluginFilepath": "/home/viktor/Work/homepage/node_modules/gatsby/dist/internal-plugins/component-layout-creator",
      "packageJson": {
        "name": "component-layout-creator",
        "description": "An internal Gatsby plugin that creates pages from component files in src/layouts",
        "version": "1.0.0",
        "main": "index.js",
        "keywords": [
          "gatsby",
          "gatsby-plugin"
        ],
        "author": "Kyle Mathews <mathews.kyle@gmail.com>",
        "license": "MIT",
        "dependencies": [],
        "devDependencies": [],
        "peerDependencies": [],
        "optionalDependecies": [],
        "bundledDependecies": []
      },
      "parent": "SOURCE",
      "children": [],
      "internal": {
        "contentDigest": "0f2d6418533a9a05af2b21175d62e84e",
        "type": "SitePlugin",
        "owner": "internal-data-bridge"
      }
    },
    "Plugin internal-data-bridge": {
      "resolve": "/home/viktor/Work/homepage/node_modules/gatsby/dist/internal-plugins/internal-data-bridge",
      "id": "Plugin internal-data-bridge",
      "name": "internal-data-bridge",
      "version": "1.0.0",
      "pluginOptions": {
        "plugins": []
      },
      "nodeAPIs": [
        "sourceNodes",
        "onCreatePage"
      ],
      "browserAPIs": [],
      "ssrAPIs": [],
      "pluginFilepath": "/home/viktor/Work/homepage/node_modules/gatsby/dist/internal-plugins/internal-data-bridge",
      "packageJson": {
        "name": "internal-data-bridge",
        "description": "An internal Gatsby plugin which creates data nodes from internal data",
        "version": "1.0.0",
        "main": "index.js",
        "author": "Kyle Mathews <mathews.kyle@gmail.com>",
        "license": "MIT",
        "dependencies": [],
        "devDependencies": [],
        "peerDependencies": [],
        "optionalDependecies": [],
        "bundledDependecies": []
      },
      "parent": "SOURCE",
      "children": [],
      "internal": {
        "contentDigest": "010c057ebb278386398fff131aaa47bb",
        "type": "SitePlugin",
        "owner": "internal-data-bridge"
      }
    },
    "Plugin prod-404": {
      "resolve": "/home/viktor/Work/homepage/node_modules/gatsby/dist/internal-plugins/prod-404",
      "id": "Plugin prod-404",
      "name": "prod-404",
      "version": "1.0.0",
      "pluginOptions": {
        "plugins": []
      },
      "nodeAPIs": [
        "onCreatePage"
      ],
      "browserAPIs": [],
      "ssrAPIs": [],
      "pluginFilepath": "/home/viktor/Work/homepage/node_modules/gatsby/dist/internal-plugins/prod-404",
      "packageJson": {
        "name": "prod-404",
        "description": "Internal plugin to detect various flavors of 404 pages and ensure there's a 404.html path created as well to ensure compatability with static hosts",
        "version": "1.0.0",
        "main": "index.js",
        "author": "Kyle Mathews <mathews.kyle@gmail.com>",
        "license": "MIT",
        "dependencies": [],
        "devDependencies": [],
        "peerDependencies": [],
        "optionalDependecies": [],
        "bundledDependecies": []
      },
      "parent": "SOURCE",
      "children": [],
      "internal": {
        "contentDigest": "e1c8f9e22d27c5ce6517e19419399db0",
        "type": "SitePlugin",
        "owner": "internal-data-bridge"
      }
    },
    "Plugin query-runner": {
      "resolve": "/home/viktor/Work/homepage/node_modules/gatsby/dist/internal-plugins/query-runner",
      "id": "Plugin query-runner",
      "name": "query-runner",
      "version": "1.0.0",
      "pluginOptions": {
        "plugins": []
      },
      "nodeAPIs": [
        "onCreatePage",
        "onCreateLayout"
      ],
      "browserAPIs": [],
      "ssrAPIs": [],
      "pluginFilepath": "/home/viktor/Work/homepage/node_modules/gatsby/dist/internal-plugins/query-runner",
      "packageJson": {
        "name": "query-runner",
        "description": "Internal plugin for running queries",
        "version": "1.0.0",
        "main": "index.js",
        "author": "",
        "license": "MIT",
        "dependencies": [],
        "devDependencies": [],
        "peerDependencies": [],
        "optionalDependecies": [],
        "bundledDependecies": []
      },
      "parent": "SOURCE",
      "children": [],
      "internal": {
        "contentDigest": "8f0f61e6ae192bf2a0c242855d7cec00",
        "type": "SitePlugin",
        "owner": "internal-data-bridge"
      }
    },
    "Plugin gatsby-plugin-react-helmet": {
      "resolve": "/home/viktor/Work/homepage/node_modules/gatsby-plugin-react-helmet",
      "id": "Plugin gatsby-plugin-react-helmet",
      "name": "gatsby-plugin-react-helmet",
      "version": "2.0.11",
      "pluginOptions": {
        "plugins": []
      },
      "nodeAPIs": [],
      "browserAPIs": [],
      "ssrAPIs": [
        "onRenderBody"
      ],
      "pluginFilepath": "/home/viktor/Work/homepage/node_modules/gatsby-plugin-react-helmet",
      "packageJson": {
        "name": "gatsby-plugin-react-helmet",
        "description": "Manage document head data with react-helmet. Provides drop-in server rendering support for Gatsby.",
        "version": "2.0.11",
        "main": "index.js",
        "keywords": [
          "gatsby",
          "gatsby-plugin",
          "favicon",
          "react-helmet",
          "seo",
          "document",
          "head",
          "title",
          "meta",
          "link",
          "script",
          "base",
          "noscript",
          "style"
        ],
        "author": "Kyle Mathews <matthews.kyle@gmail.com>",
        "license": "MIT",
        "dependencies": [
          {
            "name": "babel-runtime",
            "version": "^6.26.0"
          }
        ],
        "devDependencies": [
          {
            "name": "babel-cli",
            "version": "^6.26.0"
          },
          {
            "name": "cross-env",
            "version": "^5.0.5"
          }
        ],
        "peerDependencies": [
          {
            "name": "gatsby",
            "version": "^1.0.0"
          },
          {
            "name": "react-helmet",
            "version": ">=5.1.3"
          }
        ],
        "optionalDependecies": [],
        "bundledDependecies": []
      },
      "parent": "SOURCE",
      "children": [],
      "internal": {
        "contentDigest": "0d178c59d5196cb8ee4c8f1a7f604dae",
        "type": "SitePlugin",
        "owner": "internal-data-bridge"
      }
    },
    "Plugin gatsby-plugin-postcss-sass": {
      "resolve": "/home/viktor/Work/homepage/node_modules/gatsby-plugin-postcss-sass",
      "id": "Plugin gatsby-plugin-postcss-sass",
      "name": "gatsby-plugin-postcss-sass",
      "version": "1.0.21",
      "pluginOptions": {
        "plugins": [],
        "precision": "8",
        "includePaths": [
          "/home/viktor/Work/homepage/node_modules",
          "/home/viktor/Work/homepage/node_modules/bootstrap-sass/assets/stylesheets",
          "/home/viktor/Work/homepage/node_modules/layout-grid/sass",
          "/home/viktor/Work/homepage/node_modules/slick-carousel/slick"
        ],
        "postCssPlugins": [
          null
        ]
      },
      "nodeAPIs": [
        "modifyWebpackConfig"
      ],
      "browserAPIs": [],
      "ssrAPIs": [],
      "pluginFilepath": "/home/viktor/Work/homepage/node_modules/gatsby-plugin-postcss-sass",
      "packageJson": {
        "name": "gatsby-plugin-postcss-sass",
        "description": "Gatsby plugin to handle scss/sass files with integrated support for also processing with Postcss plugins",
        "version": "1.0.21",
        "main": "index.js",
        "keywords": [
          "gatsby",
          "gatsby-plugin",
          "postcss",
          "sass",
          "scss"
        ],
        "author": "Scotty Eckenthal <scotty@meetfabric.com>",
        "license": "MIT",
        "dependencies": [
          {
            "name": "babel-runtime",
            "version": "^6.26.0"
          },
          {
            "name": "gatsby-1-config-css-modules",
            "version": "^1.0.11"
          },
          {
            "name": "gatsby-1-config-extract-plugin",
            "version": "^1.0.3"
          },
          {
            "name": "node-sass",
            "version": "^4.5.2"
          },
          {
            "name": "sass-loader",
            "version": "^4.1.1"
          }
        ],
        "devDependencies": [
          {
            "name": "babel-cli",
            "version": "^6.26.0"
          },
          {
            "name": "cross-env",
            "version": "^5.0.5"
          }
        ],
        "peerDependencies": [
          {
            "name": "gatsby",
            "version": "^1.0.0"
          }
        ],
        "optionalDependecies": [],
        "bundledDependecies": []
      },
      "parent": "SOURCE",
      "children": [],
      "internal": {
        "contentDigest": "ee17c62b983625dcf77ba91a48af7970",
        "type": "SitePlugin",
        "owner": "internal-data-bridge"
      }
    },
    "Plugin default-site-plugin": {
      "resolve": "/home/viktor/Work/homepage",
      "id": "Plugin default-site-plugin",
      "name": "default-site-plugin",
      "version": "da4c5343e8803a138b3d41cc233f2eb4",
      "pluginOptions": {
        "plugins": []
      },
      "nodeAPIs": [
        "modifyWebpackConfig"
      ],
      "browserAPIs": [
        "onInitialClientRender"
      ],
      "ssrAPIs": [],
      "pluginFilepath": "/home/viktor/Work/homepage",
      "packageJson": {
        "name": "homepage",
        "description": "Enhancv Homepage",
        "version": "2.1.0",
        "main": "index.js",
        "license": "MIT",
        "dependencies": [
          {
            "name": "bootstrap-sass",
            "version": "^3.3.7"
          },
          {
            "name": "browser-sync",
            "version": "^2.18.11"
          },
          {
            "name": "classnames",
            "version": "^2.2.5"
          },
          {
            "name": "del",
            "version": "^2.2.2"
          },
          {
            "name": "dotenv",
            "version": "^2.0.0"
          },
          {
            "name": "fs",
            "version": "^0.0.1-security"
          },
          {
            "name": "gatsby",
            "version": "^1.9.247"
          },
          {
            "name": "gatsby-link",
            "version": "^1.6.40"
          },
          {
            "name": "gatsby-plugin-postcss-sass",
            "version": "^1.0.21"
          },
          {
            "name": "gatsby-plugin-react-helmet",
            "version": "^2.0.10"
          },
          {
            "name": "gatsby-plugin-sass",
            "version": "^1.0.26"
          },
          {
            "name": "layout-grid",
            "version": "^2.2.0"
          },
          {
            "name": "react",
            "version": "16.3"
          },
          {
            "name": "react-helmet",
            "version": "^5.2.0"
          },
          {
            "name": "react-slick",
            "version": "^0.23.1"
          },
          {
            "name": "react-tilt",
            "version": "^0.1.4"
          },
          {
            "name": "scrollreveal",
            "version": "^3.3.6"
          },
          {
            "name": "slick-carousel",
            "version": "^1.8.1"
          },
          {
            "name": "sourcebuster",
            "version": "^1.1.0"
          },
          {
            "name": "stickyfill",
            "version": "git+https://github.com/wilddeer/stickyfill.git#1.1.4"
          },
          {
            "name": "switch-toggle",
            "version": "^1.0.1"
          },
          {
            "name": "validate.js",
            "version": "^0.11.1"
          },
          {
            "name": "whatwg-fetch",
            "version": "^2.0.4"
          }
        ],
        "devDependencies": [
          {
            "name": "prettier-ecv",
            "version": "^1.7.0"
          }
        ],
        "peerDependencies": [],
        "optionalDependecies": [],
        "bundledDependecies": []
      },
      "parent": "SOURCE",
      "children": [],
      "internal": {
        "contentDigest": "785d3ac8165f357d93b11cea8f40964c",
        "type": "SitePlugin",
        "owner": "internal-data-bridge"
      }
    },
    "Site": {
      "siteMetadata": {
        "title": "Gatsby Default Starter"
      },
      "port": "8000",
      "host": "localhost",
      "pathPrefix": "",
      "polyfill": true,
      "buildTime": "2018-06-05T11:56:34.325Z",
      "id": "Site",
      "parent": "SOURCE",
      "children": [],
      "internal": {
        "contentDigest": "d2eb8e187895636f5d28d52f12d2be8a",
        "type": "Site",
        "owner": "internal-data-bridge"
      }
    },
    "SitePage /404/": {
      "layout": "index",
      "jsonName": "404.json",
      "internalComponentName": "Component404",
      "path": "/404/",
      "component": "/home/viktor/Work/homepage/src/pages/404.js",
      "componentChunkName": "component---src-pages-404-js",
      "context": {},
      "pluginCreator___NODE": "Plugin component-page-creator",
      "pluginCreatorId": "Plugin component-page-creator",
      "componentPath": "/home/viktor/Work/homepage/src/pages/404.js",
      "id": "SitePage /404/",
      "parent": "SOURCE",
      "children": [],
      "internal": {
        "type": "SitePage",
        "contentDigest": "20ae2be3d1100f4e93cfb4073f11e49c",
        "description": "Plugin component-page-creator",
        "owner": "internal-data-bridge"
      }
    },
    "SitePage /about/": {
      "layout": "index",
      "jsonName": "about.json",
      "internalComponentName": "ComponentAbout",
      "path": "/about/",
      "component": "/home/viktor/Work/homepage/src/pages/about.js",
      "componentChunkName": "component---src-pages-about-js",
      "context": {},
      "pluginCreator___NODE": "Plugin component-page-creator",
      "pluginCreatorId": "Plugin component-page-creator",
      "componentPath": "/home/viktor/Work/homepage/src/pages/about.js",
      "id": "SitePage /about/",
      "parent": "SOURCE",
      "children": [],
      "internal": {
        "type": "SitePage",
        "contentDigest": "5d2917ed8e97087b23b90e881128eeda",
        "description": "Plugin component-page-creator",
        "owner": "internal-data-bridge"
      }
    },
    "SitePage /careers/": {
      "layout": "index",
      "jsonName": "careers.json",
      "internalComponentName": "ComponentCareers",
      "path": "/careers/",
      "component": "/home/viktor/Work/homepage/src/pages/careers.js",
      "componentChunkName": "component---src-pages-careers-js",
      "context": {},
      "pluginCreator___NODE": "Plugin component-page-creator",
      "pluginCreatorId": "Plugin component-page-creator",
      "componentPath": "/home/viktor/Work/homepage/src/pages/careers.js",
      "id": "SitePage /careers/",
      "parent": "SOURCE",
      "children": [],
      "internal": {
        "type": "SitePage",
        "contentDigest": "a3f0c04aa7a19bb8b89223dcbd7229e4",
        "description": "Plugin component-page-creator",
        "owner": "internal-data-bridge"
      }
    },
    "SitePage /enhancv-button/": {
      "layout": "index",
      "jsonName": "enhancv-button.json",
      "internalComponentName": "ComponentEnhancvButton",
      "path": "/enhancv-button/",
      "component": "/home/viktor/Work/homepage/src/pages/enhancv-button.js",
      "componentChunkName": "component---src-pages-enhancv-button-js",
      "context": {},
      "pluginCreator___NODE": "Plugin component-page-creator",
      "pluginCreatorId": "Plugin component-page-creator",
      "componentPath": "/home/viktor/Work/homepage/src/pages/enhancv-button.js",
      "id": "SitePage /enhancv-button/",
      "parent": "SOURCE",
      "children": [],
      "internal": {
        "type": "SitePage",
        "contentDigest": "f2d83ba43db765e5a69d4c90aee1e38e",
        "description": "Plugin component-page-creator",
        "owner": "internal-data-bridge"
      }
    },
    "SitePage /": {
      "layout": "index",
      "jsonName": "index.json",
      "internalComponentName": "ComponentIndex",
      "path": "/",
      "component": "/home/viktor/Work/homepage/src/pages/index.js",
      "componentChunkName": "component---src-pages-index-js",
      "context": {},
      "pluginCreator___NODE": "Plugin component-page-creator",
      "pluginCreatorId": "Plugin component-page-creator",
      "componentPath": "/home/viktor/Work/homepage/src/pages/index.js",
      "id": "SitePage /",
      "parent": "SOURCE",
      "children": [],
      "internal": {
        "type": "SitePage",
        "contentDigest": "b5aca1fe4bf8c457b877fbb18415d286",
        "description": "Plugin component-page-creator",
        "owner": "internal-data-bridge"
      }
    },
    "SitePage /pricing/": {
      "layout": "index",
      "jsonName": "pricing.json",
      "internalComponentName": "ComponentPricing",
      "path": "/pricing/",
      "component": "/home/viktor/Work/homepage/src/pages/pricing.js",
      "componentChunkName": "component---src-pages-pricing-js",
      "context": {},
      "pluginCreator___NODE": "Plugin component-page-creator",
      "pluginCreatorId": "Plugin component-page-creator",
      "componentPath": "/home/viktor/Work/homepage/src/pages/pricing.js",
      "id": "SitePage /pricing/",
      "parent": "SOURCE",
      "children": [],
      "internal": {
        "type": "SitePage",
        "contentDigest": "5d9b6f67110552669b240a582db6214d",
        "description": "Plugin component-page-creator",
        "owner": "internal-data-bridge"
      }
    },
    "SitePage /pricingb/": {
      "layout": "index",
      "jsonName": "pricingb.json",
      "internalComponentName": "ComponentPricingb",
      "path": "/pricingb/",
      "component": "/home/viktor/Work/homepage/src/pages/pricingb.js",
      "componentChunkName": "component---src-pages-pricingb-js",
      "context": {},
      "pluginCreator___NODE": "Plugin component-page-creator",
      "pluginCreatorId": "Plugin component-page-creator",
      "componentPath": "/home/viktor/Work/homepage/src/pages/pricingb.js",
      "id": "SitePage /pricingb/",
      "parent": "SOURCE",
      "children": [],
      "internal": {
        "type": "SitePage",
        "contentDigest": "e4c8f4d2033b8d19ddb7021d370c5c7b",
        "description": "Plugin component-page-creator",
        "owner": "internal-data-bridge"
      }
    },
    "SitePage /privacy/": {
      "layout": "index",
      "jsonName": "privacy.json",
      "internalComponentName": "ComponentPrivacy",
      "path": "/privacy/",
      "component": "/home/viktor/Work/homepage/src/pages/privacy.js",
      "componentChunkName": "component---src-pages-privacy-js",
      "context": {},
      "pluginCreator___NODE": "Plugin component-page-creator",
      "pluginCreatorId": "Plugin component-page-creator",
      "componentPath": "/home/viktor/Work/homepage/src/pages/privacy.js",
      "id": "SitePage /privacy/",
      "parent": "SOURCE",
      "children": [],
      "internal": {
        "type": "SitePage",
        "contentDigest": "c67d8e22944ca3f50f9161de879b5deb",
        "description": "Plugin component-page-creator",
        "owner": "internal-data-bridge"
      }
    },
    "SitePage /successful-resumes/": {
      "layout": "index",
      "jsonName": "successful-resumes.json",
      "internalComponentName": "ComponentSuccessfulResumes",
      "path": "/successful-resumes/",
      "component": "/home/viktor/Work/homepage/src/pages/successful-resumes.js",
      "componentChunkName": "component---src-pages-successful-resumes-js",
      "context": {},
      "pluginCreator___NODE": "Plugin component-page-creator",
      "pluginCreatorId": "Plugin component-page-creator",
      "componentPath": "/home/viktor/Work/homepage/src/pages/successful-resumes.js",
      "id": "SitePage /successful-resumes/",
      "parent": "SOURCE",
      "children": [],
      "internal": {
        "type": "SitePage",
        "contentDigest": "857ecf090003d7a27e59d3dc5544d7f5",
        "description": "Plugin component-page-creator",
        "owner": "internal-data-bridge"
      }
    },
    "SitePage /terms/": {
      "layout": "index",
      "jsonName": "terms.json",
      "internalComponentName": "ComponentTerms",
      "path": "/terms/",
      "component": "/home/viktor/Work/homepage/src/pages/terms.js",
      "componentChunkName": "component---src-pages-terms-js",
      "context": {},
      "pluginCreator___NODE": "Plugin component-page-creator",
      "pluginCreatorId": "Plugin component-page-creator",
      "componentPath": "/home/viktor/Work/homepage/src/pages/terms.js",
      "id": "SitePage /terms/",
      "parent": "SOURCE",
      "children": [],
      "internal": {
        "type": "SitePage",
        "contentDigest": "44a5184165c13e83ffd771af7b77476c",
        "description": "Plugin component-page-creator",
        "owner": "internal-data-bridge"
      }
    },
    "SitePage /404.html": {
      "layout": "index",
      "jsonName": "404-html.json",
      "internalComponentName": "Component404Html",
      "path": "/404.html",
      "component": "/home/viktor/Work/homepage/src/pages/404.js",
      "componentChunkName": "component---src-pages-404-js",
      "context": {},
      "pluginCreator___NODE": "Plugin prod-404",
      "pluginCreatorId": "Plugin prod-404",
      "componentPath": "/home/viktor/Work/homepage/src/pages/404.js",
      "id": "SitePage /404.html",
      "parent": "SOURCE",
      "children": [],
      "internal": {
        "type": "SitePage",
        "contentDigest": "e0f410843d702051ae2f5c20b9b24d25",
        "description": "Plugin prod-404",
        "owner": "internal-data-bridge"
      }
    }
  },
  "status": {
    "plugins": {},
    "PLUGINS_HASH": "bb4bc85c79c4dbacc646c54298238879"
  },
  "componentDataDependencies": {
    "nodes": {},
    "connections": {
      "SitePage": [
        "/dev-404-page/"
      ]
    }
  }
}